{
	"1": [
		{	"name":				"Roberto C. Treviño",
			"votes":			"5,337",
			"votePercent": "51.68",
			"photo":			"/img/candidates/D1_Trevino.jpeg",
			"website":		"http://voterobertotrevino.com/",
			"cityLink":		"http://www.sanantonio.gov/Council/d1",
			"phone":			"210.207.7279",
			"fb":					"https://www.facebook.com/robertotrevinotx/",
			"twitter":		"https://twitter.com/Trevino_D1/",
			"instagram":	"https://www.instagram.com/rct_d1satx/",
			"filing":			"http://www.sanantonio.gov/Portals/0/Files/Clerk/Elections/2017%20Election/D1%20-%20Roberto%20C.%20Trevino.pdf?ver=2017-01-18-122852-650" 
		}
	],
	"2": [
		{	"name":				"William “Cruz” Shaw",
			"votes":			"3,752",
			"votePercent": "56.36",
			"photo":			"/img/candidates/D2_Shaw.jpeg",
			"website":		"http://www.cruzshaw.com/",
			"cityLink":		"",
			"phone":			"",
			"fb":					"https://www.facebook.com/votecruzshaw/",
			"twitter":		"https://twitter.com/votecruzshaw",
			"instagram":	"",
			"filing":			"http://www.sanantonio.gov/Portals/0/Files/Clerk/Elections/2017%20Election/D2%20-%20William%20Shaw.pdf?ver=2017-02-07-104315-273" 
		}
	],
	"3": [
		{	"name":				"Rebecca J. Viagran",
			"votes":			"4,509",
			"votePercent": "62.12",
			"photo":			"/img/candidates/D3_Viagran.jpeg",
			"website":		"http://www.rebeccaviagran.com/",
			"cityLink":		"http://www.sanantonio.gov/Council/d3",
			"phone":			"210.207.7064",
			"fb":					"https://www.facebook.com/VoteforRebecca/",
			"twitter":		"https://twitter.com/RebeccaViagran",
			"instagram":	"",
			"filing":			"http://www.sanantonio.gov/Portals/0/Files/Clerk/Elections/2017%20Election/D3%20-%20Rebecca%20J.%20Viagran.pdf?ver=2017-01-19-171725-860" 
		}
	],
	"4": [
		{	"name":				"Rey Saldaña",
			"votes":			"3,454",
			"votePercent": "78.36",
			"photo":			"/img/candidates/D4_Saldana.jpeg",
			"website":		"http://reysaldana.com/",
			"cityLink":		"http://www.sanantonio.gov/Council/d4",
			"phone":			"210.207.7281",
			"fb":					"https://www.facebook.com/rey4sa/",
			"twitter":		"https://twitter.com/rey4sa",
			"instagram":	"https://www.instagram.com/rey4sa/",
			"filing":			"http://www.sanantonio.gov/Portals/0/Files/Clerk/Elections/2017%20Election/D4-ReySaldana.pdf" 
		}
	],
	"5": [
		{	"name":				"Shirley Gonzales",
			"votes":			"3,396",
			"votePercent": "65.8",
			"photo":			"/img/candidates/D5_Gonzales.jpeg",
			"website":		"http://www.electshirley.com/",
			"cityLink":		"http://www.sanantonio.gov/Council/d5",
			"phone":			"210.207.7043",
			"fb":					"https://www.facebook.com/electshirley/",
			"twitter":		"",
			"instagram":	"",
			"filing":			"http://www.sanantonio.gov/Portals/0/Files/Clerk/Elections/2017%20Election/D5%20-%20Shirley%20Gonzales.pdf?ver=2017-01-23-100431-940" 
		}
	],
	"6": [
		{	"name":				"Greg Brockhouse",
			"votes":			"4,708",
			"votePercent": "52.42",
			"photo":			"/img/candidates/D6_Brockhouse.png",
			"website":		"http://gregbrockhouse.com/",
			"cityLink":		"",
			"phone":			"",
			"fb":					"https://www.facebook.com/gregbrockhousecampaign/",
			"twitter":		"https://twitter.com/BrockhouseD6",
			"instagram":	"",
			"filing":			"http://www.sanantonio.gov/Portals/0/Files/Clerk/Elections/2017%20Election/D6%20-%20Greg%20Brockhouse.pdf?ver=2017-02-15-151116-793" 
		}
	],
	"7": [
		{	"name":				"Ana Sandoval",
			"votes":			"5,957",
			"votePercent": "50.79",
			"photo":			"/img/candidates/D7_Sandoval.jpeg",
			"website":		"http://anasandoval.org/",
			"cityLink":		"http://www.sanantonio.gov/Council/d7",
			"phone":			"210.207.7044",
			"fb":					"https://www.facebook.com/anasandovalSATX/",
			"twitter":		"https://twitter.com/sandovalfor7",
			"instagram":	"",
			"filing":			"http://www.sanantonio.gov/Portals/0/Files/Clerk/Elections/2017%20Election/D7%20-%20Ana%20Sandoval.pdf?ver=2017-02-15-113111-913" 
		}
	],
	"8": [
		{	"name":				"Manny Pelaez",
			"votes":			"7,084",
			"votePercent": "55.07",
			"photo":			"/img/candidates/D8_Palaez.jpeg",
			"website":		"http://www.vote4manny.com/",
			"cityLink":		"",
			"phone":			"",
			"fb":					"https://www.facebook.com/vote4manny/",
			"twitter":		"",
			"instagram":	"",
			"filing":			"http://www.sanantonio.gov/Portals/0/Files/Clerk/Elections/2017%20Election/D8%20-%20Manny%20Pelaez.pdf?ver=2017-01-20-170937-337" 
		}
	],
	"9": [
		{	"name":				"John Courage",
			"votes":			"8,489",
			"votePercent": "52.65",
			"photo":			"/img/candidates/D9_Courage.jpeg",
			"website":		"http://www.couragefor9.com/",
			"cityLink":		"",
			"phone":			"",
			"fb":					"https://www.facebook.com/couragefor9/",
			"twitter":		"https://twitter.com/couragefor9",
			"instagram":	"",
			"filing":			"http://www.sanantonio.gov/Portals/0/Files/Clerk/Elections/2017%20Election/D9%20-%20John%20Courage.pdf?ver=2017-01-18-112048-853" 
		}
	],
	"10": [
		{	"name":				"Clayton Perry",
			"votes":			"7,156",
			"votePercent": "53.09",
			"photo":			"/img/candidates/D10_Perry.jpeg",
			"website":		"http://claytonperry.org/",
			"cityLink":		"",
			"phone":			"",
			"fb":					"https://www.facebook.com/Vote4ClaytonPerry/",
			"twitter":		"",
			"instagram":	"",
			"filing":			"http://www.sanantonio.gov/Portals/0/Files/Clerk/Elections/2017%20Election/D10%20-%20Clayton%20Perry.pdf?ver=2017-01-19-141026-043" 
		}
	],
	"mayor": [
		{	"name":				"Ron Nirenberg",
			"votes":			"54,010",
			"votePercent": "54.59",
			"photo":			"/img/candidates/Mayor_Nirenberg.jpeg",
			"website":		"https://voteron.com/",
			"fb":					"https://www.facebook.com/nirenberg/",
			"twitter":		"https://twitter.com/Ron_Nirenberg",
			"instagram":	"https://www.instagram.com/ron_nirenberg/",
			"filing":			"http://www.sanantonio.gov/Portals/0/Files/Clerk/Elections/2017%20Election/M%20-%20Ron%20Nirenberg.pdf?ver=2017-01-18-124057-240",
			"video":			"http://video.klrn.org/video/2365928797/",
			"profile":		"https://therivardreport.com/councilman-ron-nirenberg-from-jazz-to-civic-leadership/" 
		}
	]
}